maya/OpenMaya.py
maya/OpenMayaAnim.py
maya/OpenMayaFX.py
maya/OpenMayaMPx.py
maya/OpenMayaRender.py
maya/OpenMayaUI.py
maya/PySideMayaIntegration.py
maya/_OpenMaya.py
maya/_OpenMayaAnim.py
maya/_OpenMayaFX.py
maya/_OpenMayaMPx.py
maya/_OpenMayaRender.py
maya/_OpenMayaUI.py
maya/__init__.py
maya/attribute_literals.py
maya/attribute_properties.py
maya/colorManagementUtilities.py
maya/decorators.py
maya/generate_attrs_json.py
maya/maya_to_py_itr.py
maya/mmc_hierarchy.py
maya/mmc_selection.py
maya/node_types.py
maya/node_types_literals.py
maya/precomp.py
maya/standalone.py
maya/utils.py
maya/analytics/AnalyticStaticNodeTypes.py
maya/analytics/AnalyticStaticNodeTypes_res.py
maya/analytics/BaseAnalytic.py
maya/analytics/Logger.py
maya/analytics/ObjectNamer.py
maya/analytics/ProgressMatrix.py
maya/analytics/Runner.py
maya/analytics/Window.py
maya/analytics/Window_res.py
maya/analytics/__init__.py
maya/analytics/analyticAnimation.py
maya/analytics/analyticAnimation_res.py
maya/analytics/analyticCachePerformance.py
maya/analytics/analyticCachePerformance_res.py
maya/analytics/analyticCharacter.py
maya/analytics/analyticCharacter_res.py
maya/analytics/analyticConnections.py
maya/analytics/analyticConnections_res.py
maya/analytics/analyticDeformers.py
maya/analytics/analyticDeformers_res.py
maya/analytics/analyticEvalManager.py
maya/analytics/analyticEvalManager_res.py
maya/analytics/analyticGPUClusters.py
maya/analytics/analyticGPUClusters_res.py
maya/analytics/analyticGPUDeformers.py
maya/analytics/analyticGPUDeformers_res.py
maya/analytics/analyticGPUTweaks.py
maya/analytics/analyticGPUTweaks_res.py
maya/analytics/analyticHIK.py
maya/analytics/analyticHIK_res.py
maya/analytics/analyticIK.py
maya/analytics/analyticIK_res.py
maya/analytics/analyticMesh.py
maya/analytics/analyticMesh_res.py
maya/analytics/analyticNodeTypes.py
maya/analytics/analyticNodeTypes_res.py
maya/analytics/analyticScheduling.py
maya/analytics/analyticScheduling_res.py
maya/analytics/analyticScripts.py
maya_mock_completion-0.1.0.dist-info/LICENSE
maya_mock_completion-0.1.0.dist-info/METADATA
maya_mock_completion-0.1.0.dist-info/WHEEL
maya_mock_completion-0.1.0.dist-info/top_level.txt
maya_mock_completion-0.1.0.dist-info/RECORD
