Metadata-Version: 2.1
Name: maya-mock-completion
Version: 0.1.0
Summary: A mock version of the Autodesk maya libraries to run code intended for maya using a regular Python interpreterfrom a virtual environment.
Home-page: https://github.com/mrbmp33/maya_mock_completion
Author: Bernat Mas Pastor
Author-email: bmp33@duck.com
License: MIT
Classifier: License :: OSI Approved :: MIT License
Classifier: Programming Language :: Python :: 3.10
Classifier: Operating System :: OS Independent
Requires-Python: >=3.10
License-File: LICENSE
Requires-Dist: cmdx >=0.6.4
Provides-Extra: dev
Requires-Dist: twine >=4.0.2 ; extra == 'dev'
